pytest_encode/__init__.py
pytest_encode/main.py
tests/__init__.py
tests/test_encode.py
pytest_encoding-1.0.dist-info/METADATA
pytest_encoding-1.0.dist-info/WHEEL
pytest_encoding-1.0.dist-info/entry_points.txt
pytest_encoding-1.0.dist-info/top_level.txt
pytest_encoding-1.0.dist-info/RECORD
